include_code/__init__.py
include_code/__main__.py
include_code/common.py
include_code/fetch.py
include_code/include_code.py
include_code/validate.py
include_code-1.0.0.dist-info/METADATA
include_code-1.0.0.dist-info/WHEEL
include_code-1.0.0.dist-info/entry_points.txt
include_code-1.0.0.dist-info/top_level.txt
include_code-1.0.0.dist-info/RECORD
