Metadata-Version: 2.1
Name: include-code
Version: 1.0.0
Summary: A pandoc filter to easily include remote code into markdown
Author: Kevin Della Schiava
Author-email: Kevin Della Schiava <dellaschiavak@gmail.com>
License: BSD
Project-URL: Homepage, https://github.com/KevinSpaghetti/include-code
Keywords: pandoc filter documentation
Requires-Python: >=3.7
Requires-Dist: urllib3 <2.0
Requires-Dist: requests
Requires-Dist: panflute
